README
setup.py
django_zendesk.egg-info/PKG-INFO
django_zendesk.egg-info/SOURCES.txt
django_zendesk.egg-info/dependency_links.txt
django_zendesk.egg-info/top_level.txt
djzendesk/__init__.py
djzendesk/models.py
djzendesk/signals.py
djzendesk/tests.py
djzendesk/urls.py
djzendesk/views.py