Metadata-Version: 1.1
Name: django-zendesk
Version: 0.0.1
Summary: Django application for handling HTTP target callbacks from Zendesk.
Home-page: https://github.com/claymation/django-zendesk
Author: Clay McClure
Author-email: clay@daemons.net
License: UNKNOWN
Keywords: zendesk
Platform: UNKNOWN
Classifier: Development Status :: 1 - Planning
Classifier: License :: OSI Approved :: BSD License
Classifier: Environment :: Web Environment
Classifier: Framework :: Django
Classifier: Intended Audience :: Developers
